{
  "app": {
    "name": "home-mcp-server",
    "environment": "development"
  },
  "logging": {
    "level": "info",
    "retentiondays": 3
  },
  "database": {
    "url": "",
    "ssl": true,
    "maxconnections": 3
  },
  "family": {
    "members": [
      {
        "name": "Gorazd",
        "email": "gorazdfilipovski@gmail.com"
      }
    ]
  },
  "notifications": {
    "from": {
      "name": "",
      "email": ""
    }
  },
  "email": {
    "smtp": {
      "host": "smtp-relay.brevo.com",
      "port": 587,
      "secure": false,
      "user": "",
      "pass": ""
    }
  },
  "maintenance": {
    "cronsecret": ""
  },
  "worker": {
    "enabled": false
  }
}
